django_unload-0.3.3.dist-info/DESCRIPTION.rst
django_unload-0.3.3.dist-info/LICENSE.txt
django_unload-0.3.3.dist-info/METADATA
django_unload-0.3.3.dist-info/RECORD
django_unload-0.3.3.dist-info/WHEEL
django_unload-0.3.3.dist-info/metadata.json
django_unload-0.3.3.dist-info/top_level.txt
unload/__init__.py
unload/base.py
unload/logic.py
unload/settings.py
unload/utils.py
unload/management/__init__.py
unload/management/commands/__init__.py
unload/management/commands/find_unnecessary_loads.py
unload/tests/__init__.py
unload/tests/test_base.py
unload/tests/test_commands.py
unload/tests/test_logic.py
unload/tests/test_utils.py
