Metadata-Version: 2.0
Name: django-unload
Version: 0.3.3
Summary: Remove unused custom Django template tags and filters
Home-page: https://github.com/Styria-Digital/django-unload
Author: Styria Digital Services
Author-email: UNKNOWN
License: MIT
Keywords: django template tag filter
Platform: UNKNOWN
Classifier: Development Status :: 3 - Alpha
Classifier: Environment :: Web Environment
Classifier: Framework :: Django
Classifier: Framework :: Django :: 1.8
Classifier: Intended Audience :: Developers
Classifier: License :: OSI Approved :: MIT License
Classifier: Operating System :: OS Independent
Classifier: Programming Language :: Python
Classifier: Programming Language :: Python :: 2
Classifier: Programming Language :: Python :: 2.7
Classifier: Programming Language :: Python :: 3
Classifier: Programming Language :: Python :: 3.4
Classifier: Programming Language :: Python :: 3.5
Classifier: Topic :: Internet :: WWW/HTTP :: Dynamic Content
Requires-Dist: django (>=1.8,<1.9)
Requires-Dist: tabulate (==0.7.5)
